fzf_wrapper/__init__.py
fzf_wrapper/fzf_wrapper.py
fzf_wrapper-0.1.7.dist-info/LICENCE
fzf_wrapper-0.1.7.dist-info/METADATA
fzf_wrapper-0.1.7.dist-info/WHEEL
fzf_wrapper-0.1.7.dist-info/top_level.txt
fzf_wrapper-0.1.7.dist-info/RECORD
