Metadata-Version: 2.1
Name: fzf-wrapper
Version: 0.1.7
Summary: Python wrapper for junegunn's fzf. Let user interactively choose from given choices
Home-page: https://github.com/JKubovy/fzf-wrapper
Author: Jan Kubovy
Author-email: JanKubovy94@gmail.com
License: MIT
Project-URL: Bug Tracker, https://github.com/JKubovy/fzf-wrapper/issues
Classifier: Programming Language :: Python :: 3
Classifier: Environment :: Console
Classifier: Intended Audience :: Developers
Classifier: License :: OSI Approved :: MIT License
Classifier: Operating System :: OS Independent
Requires-Python: >=3.6
License-File: LICENCE
